{
	"extraInfo":	{
		"playerName": "Randomizer952",
		"gpm": "32.1",
		"matchLength": "4:59",
		"dateGenerated": "2024-12-20-19-23-32"
		},
	"name": "11-6",
	"mergeComboMetalQueue": false,
	"delayBeforeStart": 306,
	"delayBeforeRepeat": 91,
	"attackPatterns": [
		{	"height": 4,	"startTime": 328,	"chain": 53,	"chainEndDelta": 80	},
		{	"height": 2,	"startTime": 1083,	"chain": 53,	"chainEndDelta": 80	},
		{	"height": 1,	"startTime": 1393,	"chain": 53,	"chainEndDelta": 80	},
		{	"height": 3,	"startTime": 1477,	"chain": 53,	"chainEndDelta": 80	},
		{	"height": 3,	"startTime": 2211,	"chain": 250,	"chainEndDelta": 330	},
		{	"height": 1,	"startTime": 3292,	"chain": 53,	"chainEndDelta": 80	},
		{	"height": 1,	"startTime": 3373,	"chain": 53,	"chainEndDelta": 80	},
		{	"height": 3,	"startTime": 3498,	"chain": 53,	"chainEndDelta": 80	},
		{	"height": 3,	"startTime": 4112,	"chain": 53,	"chainEndDelta": 80	},
		{	"height": 3,	"startTime": 4751,	"chain": 53,	"chainEndDelta": 80	},
		{	"height": 1,	"startTime": 5047,	"chain": 53,	"chainEndDelta": 80	},
		{	"height": 1,	"startTime": 5182,	"chain": 53,	"chainEndDelta": 80	},
		{	"height": 1,	"startTime": 5621,	"chain": 250,	"chainEndDelta": 330	},
		{	"height": 1,	"startTime": 6202,	"chain": 53,	"chainEndDelta": 80	},
		{	"height": 2,	"startTime": 6283,	"chain": 53,	"chainEndDelta": 80	},
		{	"height": 3,	"startTime": 6622,	"chain": 53,	"chainEndDelta": 80	},
		{	"height": 2,	"startTime": 7266,	"chain": 250,	"chainEndDelta": 330	},
		{	"height": 3,	"startTime": 8097,	"chain": 53,	"chainEndDelta": 80	},
		{	"height": 3,	"startTime": 8605,	"chain": 53,	"chainEndDelta": 80	},
		{	"height": 1,	"startTime": 9164,	"chain": 53,	"chainEndDelta": 80	},
		{	"height": 2,	"startTime": 9245,	"chain": 53,	"chainEndDelta": 80	},
		{	"height": 2,	"startTime": 9459,	"chain": 53,	"chainEndDelta": 80	},
		{	"height": 2,	"startTime": 9992,	"chain": 250,	"chainEndDelta": 330	},
		{	"height": 1,	"startTime": 10823,	"chain": 53,	"chainEndDelta": 80	},
		{	"height": 2,	"startTime": 10929,	"chain": 53,	"chainEndDelta": 80	},
		{	"height": 3,	"startTime": 11157,	"chain": 53,	"chainEndDelta": 80	},
		{	"height": 1,	"startTime": 11750,	"chain": 250,	"chainEndDelta": 330	},
		{	"height": 1,	"startTime": 12331,	"chain": 53,	"chainEndDelta": 80	},
		{	"height": 3,	"startTime": 12429,	"chain": 53,	"chainEndDelta": 80	},
		{	"height": 1,	"startTime": 12616,	"chain": 53,	"chainEndDelta": 80	},
		{	"height": 1,	"startTime": 13055,	"chain": 250,	"chainEndDelta": 330	},
		{	"height": 3,	"startTime": 13636,	"chain": 53,	"chainEndDelta": 80	},
		{	"height": 1,	"startTime": 13880,	"chain": 53,	"chainEndDelta": 80	},
		{	"height": 3,	"startTime": 13981,	"chain": 53,	"chainEndDelta": 80	},
		{	"height": 1,	"startTime": 14590,	"chain": 250,	"chainEndDelta": 330	},
		{	"height": 3,	"startTime": 15171,	"chain": 53,	"chainEndDelta": 80	},
		{	"height": 3,	"startTime": 15640,	"chain": 53,	"chainEndDelta": 80	},
		{	"height": 2,	"startTime": 16429,	"chain": 250,	"chainEndDelta": 330	},
		{	"height": 2,	"startTime": 17260,	"chain": 53,	"chainEndDelta": 80	},
		{	"width": 5,	"height": 2,	"startTime": 1,	"metal": false	},
		{	"width": 4,	"height": 1,	"startTime": 158,	"metal": false	},
		{	"width": 6,	"height": 2,	"startTime": 240,	"metal": false	},
		{	"width": 4,	"height": 2,	"startTime": 498,	"metal": false	},
		{	"width": 4,	"height": 1,	"startTime": 673,	"metal": false	},
		{	"width": 4,	"height": 1,	"startTime": 753,	"metal": false	},
		{	"width": 3,	"height": 1,	"startTime": 801,	"metal": false	},
		{	"width": 3,	"height": 1,	"startTime": 857,	"metal": false	},
		{	"width": 5,	"height": 1,	"startTime": 1279,	"metal": false	},
		{	"width": 3,	"height": 2,	"startTime": 1728,	"metal": false	},
		{	"width": 3,	"height": 1,	"startTime": 2232,	"metal": false	},
		{	"width": 3,	"height": 1,	"startTime": 2323,	"metal": false	},
		{	"width": 4,	"height": 1,	"startTime": 2414,	"metal": false	},
		{	"width": 3,	"height": 1,	"startTime": 2505,	"metal": false	},
		{	"width": 6,	"height": 1,	"startTime": 2596,	"metal": false	},
		{	"width": 4,	"height": 2,	"startTime": 2701,	"metal": false	},
		{	"width": 4,	"height": 1,	"startTime": 3249,	"metal": false	},
		{	"width": 3,	"height": 2,	"startTime": 3370,	"metal": false	},
		{	"width": 3,	"height": 1,	"startTime": 3517,	"metal": false	},
		{	"width": 3,	"height": 2,	"startTime": 3628,	"metal": false	},
		{	"width": 3,	"height": 2,	"startTime": 3775,	"metal": false	},
		{	"width": 5,	"height": 1,	"startTime": 3943,	"metal": false	},
		{	"width": 4,	"height": 1,	"startTime": 4034,	"metal": false	},
		{	"width": 4,	"height": 1,	"startTime": 4125,	"metal": false	},
		{	"width": 3,	"height": 1,	"startTime": 4605,	"metal": false	},
		{	"width": 6,	"height": 1,	"startTime": 4696,	"metal": false	},
		{	"width": 3,	"height": 1,	"startTime": 4839,	"metal": false	},
		{	"width": 6,	"height": 2,	"startTime": 4930,	"metal": false	},
		{	"width": 6,	"height": 1,	"startTime": 5610,	"metal": false	},
		{	"width": 5,	"height": 1,	"startTime": 5701,	"metal": false	},
		{	"width": 3,	"height": 2,	"startTime": 5816,	"metal": false	},
		{	"width": 3,	"height": 1,	"startTime": 5962,	"metal": false	},
		{	"width": 6,	"height": 1,	"startTime": 6053,	"metal": true	},
		{	"width": 3,	"height": 2,	"startTime": 6180,	"metal": false	},
		{	"width": 5,	"height": 1,	"startTime": 6325,	"metal": false	},
		{	"width": 5,	"height": 1,	"startTime": 6775,	"metal": false	},
		{	"width": 3,	"height": 2,	"startTime": 6885,	"metal": false	},
		{	"width": 4,	"height": 1,	"startTime": 7126,	"metal": false	},
		{	"width": 4,	"height": 1,	"startTime": 7217,	"metal": false	},
		{	"width": 6,	"height": 1,	"startTime": 7308,	"metal": true	},
		{	"width": 4,	"height": 1,	"startTime": 7399,	"metal": false	},
		{	"width": 6,	"height": 1,	"startTime": 7858,	"metal": true	},
		{	"width": 4,	"height": 1,	"startTime": 7972,	"metal": false	},
		{	"width": 4,	"height": 1,	"startTime": 8063,	"metal": false	},
		{	"width": 3,	"height": 1,	"startTime": 8187,	"metal": false	},
		{	"width": 3,	"height": 2,	"startTime": 8295,	"metal": false	},
		{	"width": 3,	"height": 1,	"startTime": 8425,	"metal": false	},
		{	"width": 6,	"height": 1,	"startTime": 8516,	"metal": false	},
		{	"width": 6,	"height": 1,	"startTime": 8965,	"metal": true	},
		{	"width": 4,	"height": 2,	"startTime": 9066,	"metal": false	},
		{	"width": 3,	"height": 1,	"startTime": 9581,	"metal": false	},
		{	"width": 3,	"height": 1,	"startTime": 9688,	"metal": false	},
		{	"width": 4,	"height": 1,	"startTime": 9779,	"metal": false	},
		{	"width": 6,	"height": 2,	"startTime": 9895,	"metal": false	},
		{	"width": 3,	"height": 1,	"startTime": 10557,	"metal": false	},
		{	"width": 3,	"height": 1,	"startTime": 10663,	"metal": false	},
		{	"width": 5,	"height": 1,	"startTime": 10754,	"metal": false	},
		{	"width": 5,	"height": 1,	"startTime": 10880,	"metal": false	},
		{	"width": 3,	"height": 2,	"startTime": 10986,	"metal": false	},
		{	"width": 4,	"height": 2,	"startTime": 11223,	"metal": false	},
		{	"width": 3,	"height": 2,	"startTime": 11490,	"metal": false	},
		{	"width": 3,	"height": 2,	"startTime": 11666,	"metal": false	},
		{	"width": 6,	"height": 1,	"startTime": 11899,	"metal": true	},
		{	"width": 3,	"height": 2,	"startTime": 12009,	"metal": false	},
		{	"width": 3,	"height": 1,	"startTime": 12149,	"metal": false	},
		{	"width": 5,	"height": 1,	"startTime": 12240,	"metal": false	},
		{	"width": 5,	"height": 1,	"startTime": 12331,	"metal": false	},
		{	"width": 3,	"height": 1,	"startTime": 12435,	"metal": false	},
		{	"width": 4,	"height": 1,	"startTime": 12530,	"metal": false	},
		{	"width": 3,	"height": 1,	"startTime": 12979,	"metal": false	},
		{	"width": 4,	"height": 1,	"startTime": 13070,	"metal": false	},
		{	"width": 5,	"height": 1,	"startTime": 13161,	"metal": false	},
		{	"width": 3,	"height": 2,	"startTime": 13253,	"metal": false	},
		{	"width": 3,	"height": 2,	"startTime": 13455,	"metal": false	},
		{	"width": 3,	"height": 2,	"startTime": 13658,	"metal": false	},
		{	"width": 4,	"height": 1,	"startTime": 13848,	"metal": false	},
		{	"width": 5,	"height": 2,	"startTime": 13951,	"metal": false	},
		{	"width": 6,	"height": 1,	"startTime": 14529,	"metal": false	},
		{	"width": 5,	"height": 2,	"startTime": 14620,	"metal": false	},
		{	"width": 4,	"height": 2,	"startTime": 15301,	"metal": false	},
		{	"width": 5,	"height": 2,	"startTime": 15549,	"metal": false	},
		{	"width": 5,	"height": 1,	"startTime": 15815,	"metal": false	},
		{	"width": 4,	"height": 1,	"startTime": 15922,	"metal": false	},
		{	"width": 6,	"height": 2,	"startTime": 16013,	"metal": false	},
		{	"width": 3,	"height": 2,	"startTime": 16563,	"metal": false	},
		{	"width": 3,	"height": 1,	"startTime": 16757,	"metal": false	},
		{	"width": 5,	"height": 1,	"startTime": 16848,	"metal": false	},
		{	"width": 5,	"height": 2,	"startTime": 16939,	"metal": false	},
		{	"width": 5,	"height": 1,	"startTime": 17480,	"metal": false	},
		{	"width": 4,	"height": 1,	"startTime": 17575,	"metal": false	},
	]
}
